{"title":"Combined feed","url":"https://TicketOpen.github.io/records/all.xml","elements":[{"title":"GLDN x PAKK x US​:​WE 스플릿 앨범 ‘「玖 / jiǔ」: 3-way split’ CD음반 (공상온도 스토어 ─ 음반)","contents":"25,000 won","link":"http://shopondo.cafe24.com/product/detail.html?product_no=1844&cate_no=60&display_group=1","retrieved":1663784042336,"image":"http://shopondo.cafe24.com/web/product/medium/202201/2c771328bb4769ca613e4a1ff8feb206.jpg"},{"title":"웨스턴 카잇 Western Kite 정규 ‘ultraviolet!’ CD음반+카달로그 (공상온도 스토어 ─ 음반)","contents":"23,000 won","link":"http://shopondo.cafe24.com/product/detail.html?product_no=1843&cate_no=60&display_group=1","retrieved":1663784042337,"image":"http://shopondo.cafe24.com/web/product/medium/202201/1f58decdeccdd3f929ace8d8843577a8.jpg"},{"title":"온더달 ONTHEDAL EP ‘℃ dal’ CD음반 (공상온도 스토어 ─ 음반)","contents":"15,000 won","link":"http://shopondo.cafe24.com/product/detail.html?product_no=1842&cate_no=60&display_group=1","retrieved":1663784042349,"image":"http://shopondo.cafe24.com/web/product/medium/202201/853d91e413493e2b3586616ac62d93b5.jpg"},{"title":"폴립 POLYP 3rd EP ‘The Cinema’ CD음반 (공상온도 스토어 ─ 음반)","contents":"13,000 won","link":"http://shopondo.cafe24.com/product/detail.html?product_no=1816&cate_no=60&display_group=1","retrieved":1663784042352,"image":"http://shopondo.cafe24.com/web/product/medium/202111/013f7cfb89b7d34fcca379cbe144f273.jpg"},{"title":"{ 재입고 } 다린 Darin 3rd EP ‘갈래’ CD음반 (공상온도 스토어 ─ 음반)","contents":"15,000 won","link":"http://shopondo.cafe24.com/product/detail.html?product_no=1815&cate_no=60&display_group=1","retrieved":1663784042352,"image":"http://shopondo.cafe24.com/web/product/medium/202111/7ad984731967a183940544c125bcbb89.jpg"},{"title":"십개월의 미래 Ten Months 모임 별 Byul.org , 남궁선 시나리오집 + CD 결합 음반 / 한정반 (공상온도 스토어 ─ 음반)","contents":"23,000 won","link":"http://shopondo.cafe24.com/product/detail.html?product_no=1810&cate_no=60&display_group=1","retrieved":1663784042354,"image":"http://shopondo.cafe24.com/web/product/medium/202110/9b70820381c0890717c2a786604ee729.jpg"},{"title":"양창근 정규2집 ‘WAVE’ CD음반 (공상온도 스토어 ─ 음반)","contents":"17,000 won","link":"http://shopondo.cafe24.com/product/detail.html?product_no=1806&cate_no=60&display_group=1","retrieved":1663784042356,"image":"http://shopondo.cafe24.com/web/product/medium/202110/7d7d4b4dd65c1b5809bd80457de30fab.jpg"},{"title":"전파사(電波寺) 정규1집 ‘억겁의 싸이-키’  CD음반 (공상온도 스토어 ─ 음반)","contents":"14,000 won","link":"http://shopondo.cafe24.com/product/detail.html?product_no=1804&cate_no=60&display_group=1","retrieved":1663784042357,"image":"http://shopondo.cafe24.com/web/product/medium/202109/ca47c1423dbc900935b21f3c3e37ca79.jpg"},{"title":"시크릿 아시안 맨 Secret Asian Men 2집 Ghost CD/음반 (일렉트릭 뮤즈) (공상온도 스토어 ─ 음반)","contents":"16,300 won","link":"http://shopondo.cafe24.com/product/detail.html?product_no=1775&cate_no=60&display_group=1","retrieved":1663784042358,"image":"http://shopondo.cafe24.com/web/product/medium/202106/7239b1d8de8436a5cd4d7c0eb4af7032.jpg"},{"title":"{ 2차재입고 } 천용성 정규 2집 '수몰' CD/음반 (브로마이드 증정 / 오소리웍스) (공상온도 스토어 ─ 음반)","contents":"22,000 won","link":"http://shopondo.cafe24.com/product/detail.html?product_no=1784&cate_no=60&display_group=1","retrieved":1663784042365,"image":"http://shopondo.cafe24.com/web/product/medium/202107/22ff2a1364c828c27d9bd7f53876e6df.jpg"},{"title":"다정 Dajung 1집 Jay Knife CD/음반 (일렉트릭 뮤즈) (공상온도 스토어 ─ 음반)","contents":"16,300 won","link":"http://shopondo.cafe24.com/product/detail.html?product_no=1772&cate_no=60&display_group=1","retrieved":1663784042365,"image":"http://shopondo.cafe24.com/web/product/medium/202106/6ca41437d9e6ea4ac984953bbfe11acb.jpg"},{"title":"로우 행잉 프루츠 Low Hanging Fruits EP I Just Wanna Be Better CD음반 (공상온도 스토어 ─ 음반)","contents":"13,000 won","link":"http://shopondo.cafe24.com/product/detail.html?product_no=1756&cate_no=60&display_group=1","retrieved":1663784042365,"image":"http://shopondo.cafe24.com/web/product/medium/202105/124303bafb53a56d69cd5282b36c52dd.jpg"},{"title":"빅베트(Bigbet) EP ‘타인의 마음’ 빅베이비드라이버 트리오 CD음반 (일렉트릭 뮤즈) (공상온도 스토어 ─ 음반)","contents":"11,900 won","link":"http://shopondo.cafe24.com/product/detail.html?product_no=1734&cate_no=60&display_group=1","retrieved":1663784042366,"image":"http://shopondo.cafe24.com/web/product/medium/202105/2fcbc5df664d610a0b8b724eeb10457c.jpg"},{"title":"{ 4차 재입고 } 안다영 Dayoung Ahn 정규 1집 ‘ANTIHERO’ (CD + POSTER 합본) (공상온도 스토어 ─ 음반)","contents":"35,000 won","link":"http://shopondo.cafe24.com/product/detail.html?product_no=1716&cate_no=60&display_group=1","retrieved":1663784042371,"image":"http://shopondo.cafe24.com/web/product/medium/202104/a74ce3accb1bad7ed1cd4763938f9ed7.jpg"},{"title":"안다영 Dayoung Ahn ‘ANTIHERO’ 파노라마 폴딩 포스터 POSTER (공상온도 스토어 ─ 음반)","contents":"15,000 won","link":"http://shopondo.cafe24.com/product/detail.html?product_no=1715&cate_no=60&display_group=1","retrieved":1663784042371,"image":"http://shopondo.cafe24.com/web/product/medium/202104/67399f7696f9b2ada8cd67020ca8f806.jpg"},{"title":"{ 5차재입고 } 안다영 Dayoung Ahn 정규 1집 ‘ANTIHERO’ CD음반 (공상온도 스토어 ─ 음반)","contents":"20,000 won","link":"http://shopondo.cafe24.com/product/detail.html?product_no=1714&cate_no=60&display_group=1","retrieved":1663784042371,"image":"http://shopondo.cafe24.com/web/product/medium/202104/da99811b02cdb86baa9ce3ca2da07bfd.jpg"},{"title":"빌리카터 BILLY CARTER 1집 Here I Am CD/음반 (일렉트릭 뮤즈) (공상온도 스토어 ─ 음반)","contents":"13,400 won","link":"http://shopondo.cafe24.com/product/detail.html?product_no=1761&cate_no=60&display_group=1","retrieved":1663784042372,"image":"http://shopondo.cafe24.com/web/product/medium/202106/c36effde34e5e927d260d409906144ea.jpg"},{"title":"드린지 오 Dringe Augh 3집 Black Hyll Side CD/음반 (일렉트릭 뮤즈) (공상온도 스토어 ─ 음반)","contents":"14,900 won","link":"http://shopondo.cafe24.com/product/detail.html?product_no=1759&cate_no=60&display_group=1","retrieved":1663784042372,"image":"http://shopondo.cafe24.com/web/product/medium/202106/63c8aa5cab4385aa409e9b1f84059869.jpg"},{"title":"COSMOS 모리 MORI's 1st EP Album 음반, 엽서4매, 스티커 SET (공상온도 스토어 ─ 음반)","contents":"20,000 won","link":"http://shopondo.cafe24.com/product/detail.html?product_no=1710&cate_no=60&display_group=1","retrieved":1663784042374,"image":"http://shopondo.cafe24.com/web/product/medium/202103/52579673db75602707fbed7237f21a6e.jpg"},{"title":"We, Do It Together VA_Various Artists CD음반 (일렉트릭 뮤즈) (공상온도 스토어 ─ 음반)","contents":"16,300 won","link":"http://shopondo.cafe24.com/product/detail.html?product_no=1746&cate_no=60&display_group=1","retrieved":1663784042375,"image":"http://shopondo.cafe24.com/web/product/medium/202105/e2ca7fa65a52e7b8c44f2cf2c2e3a81a.jpg"},{"title":"빅베트(Bigbet) 1집 - ‘bbdTrio’ 빅베이비드라이버 트리오 CD음반 (일렉트릭 뮤즈) (공상온도 스토어 ─ 음반)","contents":"13,400 won","link":"http://shopondo.cafe24.com/product/detail.html?product_no=1735&cate_no=60&display_group=1","retrieved":1663784042377,"image":"http://shopondo.cafe24.com/web/product/medium/202105/6ccf798084c9885030f197ab4a6b28fb.jpg"},{"title":"Walking Cliché Sextet 'Chase Reflex' 바이닐+아트북 Night Birds 나이트 버즈 (공상온도 스토어 ─ 음반)","contents":"30,000 won","link":"http://shopondo.cafe24.com/product/detail.html?product_no=1672&cate_no=60&display_group=1","retrieved":1663784042399,"image":"http://shopondo.cafe24.com/web/product/medium/202102/869aa86ed011946f5a9205b933a0d8e4.jpg"},{"title":"{ 재입고 } 스쿼시바인즈 CD음반 '신세계' (공상온도 스토어 ─ 음반)","contents":"15,000 won","link":"http://shopondo.cafe24.com/product/detail.html?product_no=1597&cate_no=60&display_group=1","retrieved":1663784042399,"image":"http://shopondo.cafe24.com/web/product/medium/202011/0c797286f685d3d077698b4fa493ae8c.jpg"},{"title":"초현(Chohyun) 싱글2집 ‘Song from the moon’ 앨범 + 그립톡 한정판 패키지 (공상온도 스토어 ─ 음반)","contents":"18,000 won","link":"http://shopondo.cafe24.com/product/detail.html?product_no=1532&cate_no=60&display_group=1","retrieved":1663784042406,"image":"http://shopondo.cafe24.com/web/product/medium/202008/288c9d7a4733eb7cad93feb1a30c7cc6.jpg"},{"title":"Afterwork#1: Dive In You 김진범 음반형 독립출판물 (공상온도 스토어 ─ 음반)","contents":"3,500 won","link":"http://shopondo.cafe24.com/product/detail.html?product_no=1527&cate_no=60&display_group=1","retrieved":1663784042409,"image":"http://shopondo.cafe24.com/web/product/medium/202008/243c6c94506b5026fe2f22c9fc812066.jpg"},{"title":"{ 8차재입고 } Dabda 다브다 정규 1집 But, All The Shining Things Are (공상온도 스토어 ─ 음반)","contents":"17,000 won","link":"http://shopondo.cafe24.com/product/detail.html?product_no=1478&cate_no=60&display_group=1","retrieved":1663784042410,"image":"http://shopondo.cafe24.com/web/product/medium/20200627/c6a4f3e639306f9e43a11e125ef404aa.jpg"},{"title":"이야기, 멀고도 가까운 : 여성 싱어송라이터 다섯 사람의 말과 노래로 기록한 ‘나’의 시공간 인터뷰집+음반 결합된 서적 (공상온도 스토어 ─ 음반)","contents":"25,000 won","link":"http://shopondo.cafe24.com/product/detail.html?product_no=1477&cate_no=60&display_group=1","retrieved":1663784042416,"image":"http://shopondo.cafe24.com/web/product/medium/20200626/dc6258765054928ba58d4652f44b6a3b.jpg"},{"title":"Feeling of You 그립톡 싱어송라이터 윤새 (Yunsae) 싱글앨범 발매 기념 굿즈 (공상온도 스토어 ─ 음반)","contents":"8,000 won","link":"http://shopondo.cafe24.com/product/detail.html?product_no=1433&cate_no=60&display_group=1","retrieved":1663784042417,"image":"http://shopondo.cafe24.com/web/product/medium/20200527/fff98e19df095644e65e1d732c830120.jpg"},{"title":"Ohelen&Choisol 오헬렌&최솔 EP ’Oh’ (공상온도 스토어 ─ 음반)","contents":"15,000 won","link":"http://shopondo.cafe24.com/product/detail.html?product_no=1381&cate_no=60&display_group=1","retrieved":1663784042417,"image":"http://shopondo.cafe24.com/web/product/medium/20200329/45cec1a9bd2707ac4e15aa69168b15b5.jpg"},{"title":"Guinneissik 기나이직 정규 1집 ’듣는음악과 평강하지 못한’ (공상온도 스토어 ─ 음반)","contents":"15,000 won","link":"http://shopondo.cafe24.com/product/detail.html?product_no=1380&cate_no=60&display_group=1","retrieved":1663784042419,"image":"http://shopondo.cafe24.com/web/product/medium/20200329/7673e1b514e2bbc59f40a20bf38acb2c.jpg"},{"title":"{ 2차재입고 } 천용성 정규1집 '김일성이 죽던 해' CD/음반 (오소리웍스) (공상온도 스토어 ─ 음반)","contents":"15,000 won","link":"http://shopondo.cafe24.com/product/detail.html?product_no=1103&cate_no=60&display_group=1","retrieved":1663784042423,"image":"http://shopondo.cafe24.com/web/product/medium/20200218/3b12ed6a665ca3f5b5e8ac33c2f5867c.jpg"},{"title":"{ 재입고 } 애리(Airy) EP ‘SEEDS’ (공상온도 스토어 ─ 음반)","contents":"12,000 won","link":"http://shopondo.cafe24.com/product/detail.html?product_no=936&cate_no=60&display_group=1","retrieved":1663784042424,"image":"http://shopondo.cafe24.com/web/product/medium/20191118/3d03ce23bfa393015739e1d952aa6970.jpg"},{"title":"Overthinking kokopelli(코코펠리) 책 형태 음반 (공상온도 스토어 ─ 음반)","contents":"20,000 won","link":"http://shopondo.cafe24.com/product/detail.html?product_no=1334&cate_no=60&display_group=1","retrieved":1663784042425,"image":"http://shopondo.cafe24.com/web/product/medium/20200218/2feb45c6ca92ae18b3586184bf72e3a8.jpg"},{"title":"라로바의 방 비디오로즈 (강현우, 허철주) (공상온도 스토어 ─ 음반)","contents":"22,000 won","link":"http://shopondo.cafe24.com/product/detail.html?product_no=1259&cate_no=60&display_group=1","retrieved":1663784042428,"image":"http://shopondo.cafe24.com/web/product/medium/20191223/418bebdeaeab5661f91b71bd6e5ea834.jpg"},{"title":"INERTIA 양동기 음악, 근하 그래픽노블 (공상온도 스토어 ─ 음반)","contents":"13,000 won","link":"http://shopondo.cafe24.com/product/detail.html?product_no=1249&cate_no=60&display_group=1","retrieved":1663784042429,"image":"http://shopondo.cafe24.com/web/product/medium/20191202/17921d9d7f82aaecc50059e2f50fa500.jpg"},{"title":"양창근 EP 'Rainy Season' CD음반 (공상온도 스토어 ─ 음반)","contents":"12,000 won","link":"http://shopondo.cafe24.com/product/detail.html?product_no=1195&cate_no=60&display_group=1","retrieved":1663784042431,"image":"http://shopondo.cafe24.com/web/product/medium/201910/f531c070505c83c1350847550edd0c60.jpg"},{"title":"초현 EP음반 '잔혹한 자화상(a cruel portrait)' 엽서포함 세트 (공상온도 스토어 ─ 음반)","contents":"15,000 won","link":"http://shopondo.cafe24.com/product/detail.html?product_no=1160&cate_no=60&display_group=1","retrieved":1663784042438,"image":"http://shopondo.cafe24.com/web/product/medium/201909/72d15234b424fafcd98deac4aef38a0d.jpg"},{"title":"Slowlove & the city 슬로우러브앤더시티 정규1집 'Catch Up!' (공상온도 스토어 ─ 음반)","contents":"13,000 won","link":"http://shopondo.cafe24.com/product/detail.html?product_no=1142&cate_no=60&display_group=1","retrieved":1663784042442,"image":"http://shopondo.cafe24.com/web/product/medium/201908/b51a904e1bacd3f0ed61fbca0b1e680b.jpg"},{"title":"The Three Fakes EP ‘FAKES’ (공상온도 스토어 ─ 음반)","contents":"10,000 won","link":"http://shopondo.cafe24.com/product/detail.html?product_no=1022&cate_no=60&display_group=1","retrieved":1663784042446,"image":"http://shopondo.cafe24.com/web/product/medium/201905/7d330ec6176462db2c3c0eceecce2666.jpg"},{"title":"쓰다(Xeuda) EP ‘남겨진 것들’ (공상온도 스토어 ─ 음반)","contents":"13,000 won","link":"http://shopondo.cafe24.com/product/detail.html?product_no=1079&cate_no=60&display_group=1","retrieved":1663784042448,"image":"http://shopondo.cafe24.com/web/product/medium/201906/c8250e995c9014a05b458f011e3211e9.jpg"},{"title":"{ 10차 재입고 } 다브다(DABDA) EP Island of Each 저마다섬 : World Wide Edition (공상온도 스토어 ─ 음반)","contents":"15,000 won","link":"http://shopondo.cafe24.com/product/detail.html?product_no=1045&cate_no=60&display_group=1","retrieved":1663784042449,"image":"http://shopondo.cafe24.com/web/product/medium/202007/ac8b7be041026b38d05380e51d2d0f47.jpg"},{"title":"The Three Fakes 싱글앨범 ‘Q&E’ (공상온도 스토어 ─ 음반)","contents":"10,000 won","link":"http://shopondo.cafe24.com/product/detail.html?product_no=1021&cate_no=60&display_group=1","retrieved":1663784042451,"image":"http://shopondo.cafe24.com/web/product/medium/201905/58367e3f2c19fc827ba101f5398ea804.jpg"},{"title":"모즈다이브(MODSDIVE) 정규2집 'Four Wet Hands' (공상온도 스토어 ─ 음반)","contents":"14,000 won","link":"http://shopondo.cafe24.com/product/detail.html?product_no=906&cate_no=60&display_group=1","retrieved":1663784042453,"image":"http://shopondo.cafe24.com/web/product/medium/201809/3a2cf93af122a89c431c39860a1d525e.jpg"},{"title":"아날로그소년정규3집 TAPE '현장의 소리'(음원 다운로드 쿠폰 포함) (공상온도 스토어 ─ 음반)","contents":"12,000 won","link":"http://shopondo.cafe24.com/product/detail.html?product_no=756&cate_no=60&display_group=1","retrieved":1663784042455,"image":"http://shopondo.cafe24.com/web/product/medium/201803/756_shop1_170534.gif"},{"title":"Postwar Guinneissik 기나이직 ep (공상온도 스토어 ─ 음반)","contents":"15,000 won","link":"http://shopondo.cafe24.com/product/detail.html?product_no=1937&cate_no=60&display_group=1","retrieved":1663784042457,"image":"http://shopondo.cafe24.com/web/product/medium/202209/f9b0b2d08142994169c3c1e82b164461.jpg"},{"title":"해파 Haepa 정규 1집 '죽은 척하기' CD음반 (공상온도 스토어 ─ 음반)","contents":"18,000 won","link":"http://shopondo.cafe24.com/product/detail.html?product_no=1929&cate_no=60&display_group=1","retrieved":1663784042460,"image":"http://shopondo.cafe24.com/web/product/medium/202208/895388cf0593545865cc21b3d57a56a0.jpg"},{"title":"김시호 김시호 1st EP '18평방자’ CD음반 (공상온도 스토어 ─ 음반)","contents":"12,000 won","link":"http://shopondo.cafe24.com/product/detail.html?product_no=1917&cate_no=60&display_group=1","retrieved":1663784042467,"image":"http://shopondo.cafe24.com/web/product/medium/202207/e2d8551233d8a247b76ba5552363f7f1.jpg"},{"title":"더 윌리엄즈 The Williams Love Child  CD음반 (공상온도 스토어 ─ 음반)","contents":"18,000 won","link":"http://shopondo.cafe24.com/product/detail.html?product_no=1867&cate_no=60&display_group=1","retrieved":1663784042467,"image":"http://shopondo.cafe24.com/web/product/medium/202202/f0626b3fb6a4ab64004361578836b339.jpg"}]}